xyra_auth/__init__.py
xyra_auth/__main__.py
xyra_auth/config.json
xyra_auth/core.py
xyra_auth/termux_auth_lib.py
xyra_auth/sounds/error.wav
xyra_auth/sounds/startup.wav
xyra_auth/sounds/success.mp3
xyra_whatsapp-1.1.7.dist-info/licenses/LICENSE
xyra_whatsapp-1.1.7.dist-info/METADATA
xyra_whatsapp-1.1.7.dist-info/WHEEL
xyra_whatsapp-1.1.7.dist-info/entry_points.txt
xyra_whatsapp-1.1.7.dist-info/top_level.txt
xyra_whatsapp-1.1.7.dist-info/RECORD
