Metadata-Version: 2.4
Name: xyra-whatsapp
Version: 1.1.7
Summary: Xyra WhatsApp - WhatsApp Automation System
Author-email: XyraOfficial <xyraofficialsup@gmail.com>
License: MIT
Project-URL: Homepage, https://github.com/xyraofficial/xyra-whatsapp
Project-URL: Repository, https://github.com/xyraofficial/xyra-whatsapp
Project-URL: Issues, https://github.com/xyraofficial/xyra-whatsapp/issues
Keywords: whatsapp,automation,messaging,xyra,termux
Classifier: Programming Language :: Python :: 3
Classifier: Programming Language :: Python :: 3.8
Classifier: Programming Language :: Python :: 3.9
Classifier: Programming Language :: Python :: 3.10
Classifier: Programming Language :: Python :: 3.11
Classifier: Programming Language :: Python :: 3.12
Classifier: License :: OSI Approved :: MIT License
Classifier: Operating System :: OS Independent
Classifier: Operating System :: POSIX :: Linux
Classifier: Environment :: Console
Classifier: Intended Audience :: Developers
Classifier: Topic :: Security
Requires-Python: >=3.8
License-File: LICENSE
Requires-Dist: requests>=2.28.0
Requires-Dist: tabulate>=0.9.0
Requires-Dist: rich>=13.0.0
Requires-Dist: simple-term-menu>=1.6.0
Requires-Dist: fake-useragent>=1.1.0
Requires-Dist: tqdm>=4.64.0
Dynamic: license-file
